ovos_PHAL_plugin_mk1/__init__.py
ovos_PHAL_plugin_mk1/arduino.py
ovos_PHAL_plugin_mk1/version.py
ovos_PHAL_plugin_mk1-0.1.3.dist-info/LICENSE
ovos_PHAL_plugin_mk1-0.1.3.dist-info/METADATA
ovos_PHAL_plugin_mk1-0.1.3.dist-info/WHEEL
ovos_PHAL_plugin_mk1-0.1.3.dist-info/entry_points.txt
ovos_PHAL_plugin_mk1-0.1.3.dist-info/top_level.txt
ovos_PHAL_plugin_mk1-0.1.3.dist-info/zip-safe
ovos_PHAL_plugin_mk1-0.1.3.dist-info/RECORD
