Metadata-Version: 2.1
Name: ovos-PHAL-plugin-mk1
Version: 0.1.3
Summary: A PHAL plugin for mycroft
Home-page: https://github.com/OpenVoiceOS/ovos-PHAL-plugin-mk1
Author: JarbasAi
Author-email: jarbasai@mailfence.com
License: Apache-2.0
Platform: UNKNOWN
Classifier: Development Status :: 3 - Alpha
Classifier: Intended Audience :: Developers
Classifier: Topic :: Text Processing :: Linguistic
Classifier: License :: OSI Approved :: Apache Software License
Classifier: Programming Language :: Python :: 3.5
Classifier: Programming Language :: Python :: 3.6
Requires-Dist: ovos-plugin-manager>=0.0.24
Requires-Dist: ovos-mark1-utils>=0.0.1
Requires-Dist: ovos-utils>=0.0.38
Requires-Dist: pyserial~=3.0
